README.md
setup.py
RadioTrace.egg-info/PKG-INFO
RadioTrace.egg-info/SOURCES.txt
RadioTrace.egg-info/dependency_links.txt
RadioTrace.egg-info/requires.txt
RadioTrace.egg-info/top_level.txt
radiotrace/__init__.py
radiotrace/calPPS.py
radiotrace/get_projection.py
radiotrace/inference.py
radiotrace/load.py
radiotrace/locate.py
radiotrace/utils.py
radiotrace/visualize.py
radiotrace.egg-info/PKG-INFO
radiotrace.egg-info/SOURCES.txt
radiotrace.egg-info/dependency_links.txt
radiotrace.egg-info/requires.txt
radiotrace.egg-info/top_level.txt