Metadata-Version: 2.1
Name: RadioTrace
Version: 0.4.0
Summary: package for quantify early-stage LUAD progression from CT image
Home-page: https://github.com/LiJiaqi96/radiotrace
Author: Jiaqi Li
Author-email: li-jq18@mails.tsinghua.edu.cn
License: MIT
Platform: UNKNOWN
